LICENSE
pyproject.toml
readme.md
setup.py
nnInteractive/__init__.py
nnInteractive.egg-info/PKG-INFO
nnInteractive.egg-info/SOURCES.txt
nnInteractive.egg-info/dependency_links.txt
nnInteractive.egg-info/requires.txt
nnInteractive.egg-info/top_level.txt
nnInteractive/inference/__init__.py
nnInteractive/inference/inference_session.py
nnInteractive/inference/cvpr2025_challenge_baseline/__init__.py
nnInteractive/inference/cvpr2025_challenge_baseline/predict.py
nnInteractive/interaction/__init__.py
nnInteractive/interaction/point.py
nnInteractive/supervoxel/setup.py
nnInteractive/supervoxel/src/metadata.py
nnInteractive/supervoxel/src/reader.py
nnInteractive/supervoxel/src/run.py
nnInteractive/supervoxel/src/supervoxel.py
nnInteractive/supervoxel/src/sam2/__init__.py
nnInteractive/supervoxel/src/sam2/setup.py
nnInteractive/supervoxel/src/sam2/sam2/__init__.py
nnInteractive/supervoxel/src/sam2/sam2/automatic_mask_generator.py
nnInteractive/supervoxel/src/sam2/sam2/benchmark.py
nnInteractive/supervoxel/src/sam2/sam2/build_sam.py
nnInteractive/supervoxel/src/sam2/sam2/sam2_image_predictor.py
nnInteractive/supervoxel/src/sam2/sam2/sam2_video_predictor.py
nnInteractive/supervoxel/src/sam2/sam2/sam2_video_predictor_legacy.py
nnInteractive/supervoxel/src/sam2/sam2/modeling/__init__.py
nnInteractive/supervoxel/src/sam2/sam2/modeling/memory_attention.py
nnInteractive/supervoxel/src/sam2/sam2/modeling/memory_encoder.py
nnInteractive/supervoxel/src/sam2/sam2/modeling/position_encoding.py
nnInteractive/supervoxel/src/sam2/sam2/modeling/sam2_base.py
nnInteractive/supervoxel/src/sam2/sam2/modeling/sam2_utils.py
nnInteractive/supervoxel/src/sam2/sam2/modeling/backbones/__init__.py
nnInteractive/supervoxel/src/sam2/sam2/modeling/backbones/hieradet.py
nnInteractive/supervoxel/src/sam2/sam2/modeling/backbones/image_encoder.py
nnInteractive/supervoxel/src/sam2/sam2/modeling/backbones/utils.py
nnInteractive/supervoxel/src/sam2/sam2/modeling/sam/__init__.py
nnInteractive/supervoxel/src/sam2/sam2/modeling/sam/mask_decoder.py
nnInteractive/supervoxel/src/sam2/sam2/modeling/sam/prompt_encoder.py
nnInteractive/supervoxel/src/sam2/sam2/modeling/sam/transformer.py
