Metadata-Version: 2.1
Name: nnInteractive
Version: 1.1.0
Summary: Inference code for nnInteractive
Author: Helmholtz Imaging Applied Computer Vision Lab
Author-email: Fabian Isensee <f.isensee@dkfz-heidelberg.de>
License:                                  Apache License
Project-URL: homepage, https://github.com/MIC-DKFZ/nnInteractive
Keywords: deep learning,image segmentation,semantic segmentation,medical image analysis,medical image segmentation,nnU-Net,nnunet
Classifier: Development Status :: 5 - Production/Stable
Classifier: Intended Audience :: Developers
Classifier: Intended Audience :: Science/Research
Classifier: Intended Audience :: Healthcare Industry
Classifier: Programming Language :: Python :: 3
Classifier: License :: OSI Approved :: Apache Software License
Classifier: Topic :: Scientific/Engineering :: Artificial Intelligence
Classifier: Topic :: Scientific/Engineering :: Image Recognition
Classifier: Topic :: Scientific/Engineering :: Medical Science Apps.
Requires-Python: >=3.10
License-File: LICENSE
Requires-Dist: nnunetv2>=2.6
Requires-Dist: torch>=2.6
Requires-Dist: acvl-utils<0.3,>=0.2.3
Requires-Dist: batchgenerators>=0.25.1
Provides-Extra: dev
Requires-Dist: black; extra == "dev"
Requires-Dist: ruff; extra == "dev"
Requires-Dist: pre-commit; extra == "dev"
